hot_news_bachstudio/__init__.py
hot_news_bachstudio/server.py
hot_news_bachstudio/test_server.py
hot_news_bachstudio-3.1.0.dist-info/licenses/LICENSE
hot_news_bachstudio-3.1.0.dist-info/METADATA
hot_news_bachstudio-3.1.0.dist-info/WHEEL
hot_news_bachstudio-3.1.0.dist-info/entry_points.txt
hot_news_bachstudio-3.1.0.dist-info/top_level.txt
hot_news_bachstudio-3.1.0.dist-info/RECORD
