Metadata-Version: 2.4
Name: hot-news-bachstudio
Version: 3.1.0
Summary: MCP服务器：获取全网主流平台的新闻热点，支持20+平台 - BachStudio版本
Author-email: BachStudio <contact@bachstudio.com>
License: MIT
Project-URL: Homepage, https://github.com/BACH-AI-Tools/hot-news-bachstudio
Project-URL: Documentation, https://github.com/BACH-AI-Tools/hot-news-bachstudio#readme
Project-URL: Repository, https://github.com/BACH-AI-Tools/hot-news-bachstudio
Project-URL: Bug Tracker, https://github.com/BACH-AI-Tools/hot-news-bachstudio/issues
Keywords: mcp,hot-news,trending,news,热点,新闻,csdn,github,bilibili,bachstudio
Classifier: Development Status :: 4 - Beta
Classifier: Intended Audience :: Developers
Classifier: License :: OSI Approved :: MIT License
Classifier: Programming Language :: Python :: 3
Classifier: Programming Language :: Python :: 3.10
Classifier: Programming Language :: Python :: 3.11
Classifier: Programming Language :: Python :: 3.12
Classifier: Topic :: Software Development :: Libraries :: Python Modules
Classifier: Topic :: Internet :: WWW/HTTP :: Dynamic Content :: News/Diary
Requires-Python: >=3.10
License-File: LICENSE
Requires-Dist: aiohttp>=3.9.0
Requires-Dist: mcp>=0.9.0
Provides-Extra: dev
Requires-Dist: pytest>=7.0.0; extra == "dev"
Requires-Dist: pytest-asyncio>=0.21.0; extra == "dev"
Requires-Dist: black>=23.0.0; extra == "dev"
Requires-Dist: flake8>=6.0.0; extra == "dev"
Dynamic: license-file
